<?xml version="1.0" encoding="UTF-8"?>
<objects serializationModel="Studio.02.02.00">
	<object class="AudioFile" id="{2222350d-5525-4d68-87b8-55a9c64a904a}">
		<property name="assetPath">
			<value>VideoSound/EventSound_Hijacked.mp3</value>
		</property>
		<property name="frequencyInKHz">
			<value>48</value>
		</property>
		<property name="channelCount">
			<value>2</value>
		</property>
		<property name="length">
			<value>5.6639999999999997</value>
		</property>
		<relationship name="masterAssetFolder">
			<destination>{36af30cc-5272-4926-b57a-dc42473e27a5}</destination>
		</relationship>
	</object>
</objects>
